.gitignore
MANIFEST.in
README.rst
setup.cfg
setup.py
docs/HISTORY.txt
docs/LICENSE.GPL
docs/LICENSE.txt
docs/MANUAL.txt
raptus/__init__.py
raptus.navexplorer.egg-info/PKG-INFO
raptus.navexplorer.egg-info/SOURCES.txt
raptus.navexplorer.egg-info/dependency_links.txt
raptus.navexplorer.egg-info/entry_points.txt
raptus.navexplorer.egg-info/namespace_packages.txt
raptus.navexplorer.egg-info/not-zip-safe
raptus.navexplorer.egg-info/requires.txt
raptus.navexplorer.egg-info/top_level.txt
raptus/navexplorer/__init__.py
raptus/navexplorer/accordion.py
raptus/navexplorer/accordion_article.py
raptus/navexplorer/config.py
raptus/navexplorer/configure.zcml
raptus/navexplorer/contextmenu.py
raptus/navexplorer/interfaces.py
raptus/navexplorer/permissions.zcml
raptus/navexplorer/browser/__init__.py
raptus/navexplorer/browser/accordion.py
raptus/navexplorer/browser/accordion_article.py
raptus/navexplorer/browser/ajax.py
raptus/navexplorer/browser/configure.zcml
raptus/navexplorer/browser/images/close.png
raptus/navexplorer/browser/images/detach.png
raptus/navexplorer/browser/images/help.png
raptus/navexplorer/browser/images/hide.png
raptus/navexplorer/browser/images/raptus.png
raptus/navexplorer/browser/images/reload.png
raptus/navexplorer/browser/images/show.png
raptus/navexplorer/browser/images/throbber.gif
raptus/navexplorer/browser/javascript/jquery.cookie.js
raptus/navexplorer/browser/javascript/jquery.hotkeys.js
raptus/navexplorer/browser/javascript/jquery.jstree.js
raptus/navexplorer/browser/javascript/jquery.noselect.js
raptus/navexplorer/browser/javascript/jquery.urldecoder.js
raptus/navexplorer/browser/javascript/navexplorer_sidebar.js
raptus/navexplorer/browser/stylesheets/navexplorer_sidebar.css
raptus/navexplorer/browser/stylesheets/navexplorer_window.css
raptus/navexplorer/browser/templates/accordion.pt
raptus/navexplorer/browser/templates/accordion_archetypes.pt
raptus/navexplorer/browser/templates/accordion_article.pt
raptus/navexplorer/browser/templates/accordion_folder.pt
raptus/navexplorer/browser/templates/accordion_plone.pt
raptus/navexplorer/browser/templates/accordion_security.pt
raptus/navexplorer/browser/templates/navexplorer_sidebar.pt
raptus/navexplorer/browser/templates/navexplorer_view.pt
raptus/navexplorer/locales/raptus.navexplorer.pot
raptus/navexplorer/locales/rebuild.sh
