Metadata-Version: 1.0
Name: raptus.navexplorer
Version: 1.5
Summary: Provide a navigation to explore and manage plone content
Home-page: https://github.com/Raptus/raptus.navexplorer
Author: Raptus AG
Author-email: dev@raptus.com
License: GPL
Keywords: plone navigation manage explore
Platform: UNKNOWN
Classifier: Framework :: Plone
Classifier: Framework :: Zope2
Classifier: Framework :: Zope3
Classifier: Programming Language :: Python
